mlforge/__init__.py
mlforge/cleaning.py
mlforge/dashboard.py
mlforge/params.py
mlforge/plots.py
mlforge/predict.py
mlforge/train.py
mlforgex-1.1.0.dist-info/LICENSE
mlforgex-1.1.0.dist-info/METADATA
mlforgex-1.1.0.dist-info/WHEEL
mlforgex-1.1.0.dist-info/entry_points.txt
mlforgex-1.1.0.dist-info/top_level.txt
mlforgex-1.1.0.dist-info/RECORD
