Metadata-Version: 2.1
Name: mlforgex
Version: 1.1.0
Summary: Lightweight ML utility for automated training, evaluation, and prediction with CLI and Python API support
Author: Priyanshu Mathur
Author-email: mathurpriyanshu2006@gmail.com
License: MIT
Project-URL: Homepage, https://github.com/dhgefergfefruiwefhjhcduc/ML_Forgex
Project-URL: Documentation, https://dhgefergfefruiwefhjhcduc.github.io/mlforgex_documentation/
Project-URL: Source, https://github.com/dhgefergfefruiwefhjhcduc/ML_Forgex
Project-URL: Bug Tracker, https://github.com/dhgefergfefruiwefhjhcduc/ML_Forgex/issues
Classifier: License :: OSI Approved :: MIT License
Classifier: Programming Language :: Python :: 3
Classifier: Operating System :: OS Independent
Requires-Python: >=3.8
License-File: LICENSE
Requires-Dist: pandas
Requires-Dist: numpy
Requires-Dist: seaborn
Requires-Dist: matplotlib
Requires-Dist: scikit-learn
Requires-Dist: xgboost
Requires-Dist: imbalanced-learn
Requires-Dist: tqdm
Requires-Dist: scipy
Requires-Dist: requests
Requires-Dist: nltk
Requires-Dist: gensim
Requires-Dist: wordcloud
Requires-Dist: plotly
